{"description": "", "tags": [], "size": {"height": 480, "width": 640}, "objects": [{"description": "", "bitmap": null, "tags": [], "classTitle": "plates", "points": {"exterior": [[222, 7], [576, 136], [515, 310], [50, 144], [89, 5]], "interior": []}}, {"description": "", "bitmap": null, "tags": [], "classTitle": "intersection", "points": {"exterior": [[81, 33], [150, 68], [219, 92], [154, 7], [172, 6], [237, 93], [317, 115], [378, 126], [431, 87], [444, 90], [395, 126], [472, 131], [571, 134], [576, 136], [574, 146], [470, 146], [381, 136], [312, 126], [225, 103], [146, 78], [80, 48]], "interior": []}}]}