{"description": "", "tags": [], "size": {"height": 480, "width": 640}, "objects": [{"description": "", "bitmap": null, "tags": [], "classTitle": "plates", "points": {"exterior": [[53, 5], [137, 8], [544, 134], [490, 313], [15, 171]], "interior": []}}, {"description": "", "bitmap": null, "tags": [], "classTitle": "intersection", "points": {"exterior": [[42, 57], [118, 86], [185, 107], [109, 16], [123, 6], [137, 10], [123, 22], [199, 107], [264, 120], [339, 133], [389, 89], [405, 93], [360, 132], [446, 133], [525, 128], [541, 133], [538, 145], [447, 148], [345, 146], [256, 134], [187, 121], [115, 97], [40, 67]], "interior": []}}]}