{"description": "", "tags": [], "size": {"height": 480, "width": 640}, "objects": [{"description": "", "bitmap": null, "tags": [], "classTitle": "plates", "points": {"exterior": [[75, 5], [468, 5], [567, 17], [542, 199], [59, 114]], "interior": []}}, {"description": "", "bitmap": null, "tags": [], "classTitle": "intersection", "points": {"exterior": [[74, 21], [225, 51], [190, 8], [211, 6], [245, 54], [383, 76], [468, 6], [478, 9], [395, 81], [553, 101], [552, 115], [387, 89], [237, 65], [71, 29]], "interior": []}}]}