{"description": "", "tags": [], "size": {"height": 480, "width": 640}, "objects": [{"description": "", "bitmap": null, "tags": [], "classTitle": "plates", "points": {"exterior": [[265, 6], [455, 5], [379, 369], [194, 331]], "interior": []}}, {"description": "", "bitmap": null, "tags": [], "classTitle": "intersection", "points": {"exterior": [[363, 6], [374, 5], [372, 13], [379, 6], [386, 6], [373, 29], [368, 77], [361, 161], [412, 214], [408, 227], [363, 184], [369, 257], [380, 360], [380, 369], [368, 366], [357, 255], [350, 171], [350, 77]], "interior": []}}]}