{"description": "", "tags": [], "size": {"height": 480, "width": 640}, "objects": [{"description": "", "bitmap": null, "tags": [], "classTitle": "plates", "points": {"exterior": [[72, 162], [328, 79], [528, 5], [544, 4], [614, 174], [372, 259], [142, 344]], "interior": []}}, {"description": "", "bitmap": null, "tags": [], "classTitle": "intersection", "points": {"exterior": [[136, 334], [203, 280], [310, 202], [426, 142], [507, 117], [576, 97], [581, 105], [510, 128], [445, 151], [497, 157], [551, 174], [549, 195], [533, 199], [538, 182], [487, 169], [423, 160], [371, 184], [305, 223], [290, 287], [270, 294], [290, 233], [210, 288], [148, 340], [141, 345]], "interior": []}}]}