{"description": "", "tags": [], "size": {"height": 480, "width": 640}, "objects": [{"description": "", "bitmap": null, "tags": [], "classTitle": "plates", "points": {"exterior": [[234, 6], [422, 5], [430, 339], [427, 350], [423, 357], [242, 365]], "interior": []}}, {"description": "", "bitmap": null, "tags": [], "classTitle": "intersection", "points": {"exterior": [[330, 5], [340, 6], [339, 16], [346, 6], [354, 6], [344, 27], [350, 80], [365, 163], [424, 203], [425, 216], [371, 183], [391, 245], [417, 313], [428, 340], [426, 352], [419, 356], [397, 297], [357, 179], [338, 82]], "interior": []}}]}